{
  "i": 745,
  "t": "biffsodtutorial",
  "sv": 1,
  "ord": 1280,
  "c": "NEW NPC MODS",
  "n": "Biff the Understudy NPC",
  "langs": {
    "en": 0
  },
  "u": "https://github.com/Gitjas/Biff_the_Understudy_TutorialNPC_for_SoD",
  "a": "jastey",
  "sum": "This mod is designed as a tutorial for modders on how to script the basic structure needed for a SoD NPC.",
  "tags": [
    "npc",
    "story"
  ],
  "ph": [
    "SoD"
  ],
  "au": "jastey",
  "dl": "https://github.com/Gitjas/Biff_the_Understudy_TutorialNPC_for_SoD",
  "no": "This mod is meant as a tutorial for modders how to script the basic structure needed for an SoD NPC.",
  "pt": false,
  "co": [
    {
      "n": "Biff the Understudy: joinable \"tutorial\" NPC for SoD",
      "cn": 0,
      "wf": "biffsodtutorial",
      "wp": "biffsodtutorial\\biffsodtutorial.tp2",
      "wc": 0,
      "wq": "verified",
      "games": [
        "bgee",
        "eet"
      ],
      "tp2n": "Biff the Understudy: joinable \"tutorial\" NPC for SoD"
    },
    {
      "n": "Biff the Tutorial SoD NPC: Crossmod Content",
      "cn": 10,
      "wf": "biffsodtutorial",
      "wp": "biffsodtutorial\\biffsodtutorial.tp2",
      "wc": 10,
      "wq": "verified",
      "tp2n": "Biff the Tutorial SoD NPC: Crossmod Content"
    },
    {
      "n": "Use Dialogue Style for SoD Banters for Biff",
      "cn": 100,
      "wf": "biffsodtutorial",
      "wp": "biffsodtutorial\\biffsodtutorial.tp2",
      "wc": 100,
      "wq": "verified",
      "games": [
        "bgee",
        "eet"
      ],
      "no": "Uses SoD-style floating dialogue instead of text boxes",
      "tp2n": "Use Dialogue Style for SoD Banters for Biff"
    }
  ],
  "gh": {
    "o": "Gitjas",
    "r": "Biff_the_Understudy_TutorialNPC_for_SoD"
  }
}
