{
  "i": 912,
  "t": "m7multikit",
  "sv": 1,
  "ord": 540,
  "c": "KIT & CLASS MODS",
  "n": "Multi-class Multikit Mod",
  "langs": {
    "en": 0,
    "zh-cn": 1
  },
  "u": "https://github.com/CrevsDaak/m7multikit",
  "a": "Crevs Daak, FlameWing",
  "sum": "Ever wanted to play an Anti-Paladin/Necromancer/Assassin? A Kensai/Transmutator/Bounty Hunter?",
  "tags": [
    "kit"
  ],
  "ph": [
    "BG1",
    "SoD",
    "SoA",
    "ToB"
  ],
  "dl": "https://github.com/CrevsDaak/m7multikit",
  "no": "Ever wanted to play an Anti-Paladin/Necromancer/Assassin? A Kensai/Transmutator/Bounty Hunter?",
  "au": "Morpheus562",
  "co": [
    {
      "n": "Multiclass Multikit Builder",
      "cn": 0,
      "wf": "m7multikit",
      "wp": "m7multikit\\m7multikit.tp2",
      "wc": 0,
      "wq": "lcc-github"
    },
    {
      "n": "Multiclass Multikit Installer",
      "cn": 1,
      "wf": "m7multikit",
      "wp": "m7multikit\\m7multikit.tp2",
      "wc": 1,
      "wq": "lcc-github"
    },
    {
      "n": "Core Multikit Files",
      "cn": 10,
      "wf": "m7multikit",
      "wp": "m7multikit\\m7multikit.tp2",
      "wc": 10,
      "wq": "lcc-github"
    },
    {
      "n": "Multiclass Multikit Builder",
      "cn": 11,
      "wf": "m7multikit",
      "wp": "m7multikit\\m7multikit.tp2",
      "wc": 11,
      "wq": "lcc-github"
    },
    {
      "n": "Delete Premade Multikit",
      "cn": 12,
      "wf": "m7multikit",
      "wp": "m7multikit\\m7multikit.tp2",
      "wc": 12,
      "wq": "lcc-github"
    },
    {
      "n": "Multiclass Multikit Installer",
      "cn": 13,
      "wf": "m7multikit",
      "wp": "m7multikit\\m7multikit.tp2",
      "wc": 13,
      "wq": "lcc-github"
    }
  ],
  "gh": {
    "o": "CrevsDaak",
    "r": "m7multikit"
  }
}
