{
  "i": 712,
  "t": "realistic_bg2ee",
  "sv": 1,
  "ord": 170,
  "c": "PORTRAITS",
  "n": "Realistic Portraits for BG2EE",
  "no": "Override-only mod (no installer). Place files manually in the game's override folder. Selecting this mod shows portrait previews but does NOT add entries to the WeiDU log.",
  "pt": {
    "npc": {
      "0": [
        [
          "aerie",
          "portraits/realistic_bg2ee/naerie.png",
          "bg2"
        ],
        [
          "anomen",
          "portraits/realistic_bg2ee/nanomen.png",
          "bg2"
        ],
        [
          "cernd",
          "portraits/realistic_bg2ee/ncernd.png",
          "bg2"
        ],
        [
          "edwin",
          "portraits/realistic_bg2ee/edwin.png",
          "bg2"
        ],
        [
          "edwin",
          "portraits/realistic_bg2ee/nedwin.png",
          "bg2"
        ],
        [
          "haerdalis",
          "portraits/realistic_bg2ee/nhaer.png",
          "bg2"
        ],
        [
          "imoen",
          "portraits/realistic_bg2ee/imoen.png",
          "bg2"
        ],
        [
          "imoen",
          "portraits/realistic_bg2ee/nimoen.png",
          "bg2"
        ],
        [
          "jaheira",
          "portraits/realistic_bg2ee/jaheira.png",
          "bg2"
        ],
        [
          "jaheira",
          "portraits/realistic_bg2ee/njaheir.png",
          "bg2"
        ],
        [
          "jan",
          "portraits/realistic_bg2ee/njan.png",
          "bg2"
        ],
        [
          "keldorn",
          "portraits/realistic_bg2ee/nkeldor.png",
          "bg2"
        ],
        [
          "korgan",
          "portraits/realistic_bg2ee/nkorgan.png",
          "bg2"
        ],
        [
          "mazzy",
          "portraits/realistic_bg2ee/nmazzy.png",
          "bg2"
        ],
        [
          "minsc",
          "portraits/realistic_bg2ee/minsc.png",
          "bg2"
        ],
        [
          "minsc",
          "portraits/realistic_bg2ee/nminsc.png",
          "bg2"
        ],
        [
          "nalia",
          "portraits/realistic_bg2ee/nnalia.png",
          "bg2"
        ],
        [
          "sarevok",
          "portraits/realistic_bg2ee/sarevok.png",
          "bg2"
        ],
        [
          "valygar",
          "portraits/realistic_bg2ee/nvalyga.png",
          "bg2"
        ],
        [
          "viconia",
          "portraits/realistic_bg2ee/nvicon.png",
          "bg2"
        ],
        [
          "viconia",
          "portraits/realistic_bg2ee/viconia.png",
          "bg2"
        ],
        [
          "yoshimo",
          "portraits/realistic_bg2ee/njon.png",
          "bg2"
        ],
        [
          "yoshimo",
          "portraits/realistic_bg2ee/nyoshim.png",
          "bg2"
        ],
        [
          "ajantis",
          "portraits/realistic_bg2ee/ajantis.png",
          "bg2"
        ],
        [
          "alora",
          "portraits/realistic_bg2ee/alora.png",
          "bg2"
        ],
        [
          "branwen",
          "portraits/realistic_bg2ee/branwe.png",
          "bg2"
        ],
        [
          "coran",
          "portraits/realistic_bg2ee/coran.png",
          "bg2"
        ],
        [
          "dynaheir",
          "portraits/realistic_bg2ee/dynahei.png",
          "bg2"
        ],
        [
          "eldoth",
          "portraits/realistic_bg2ee/eldoth.png",
          "bg2"
        ],
        [
          "faldorn",
          "portraits/realistic_bg2ee/faldorn.png",
          "bg2"
        ],
        [
          "garrick",
          "portraits/realistic_bg2ee/garrick.png",
          "bg2"
        ],
        [
          "kagain",
          "portraits/realistic_bg2ee/kagain.png",
          "bg2"
        ],
        [
          "khalid",
          "portraits/realistic_bg2ee/khalid.png",
          "bg2"
        ],
        [
          "kivan",
          "portraits/realistic_bg2ee/kivan.png",
          "bg2"
        ],
        [
          "montaron",
          "portraits/realistic_bg2ee/montar.png",
          "bg2"
        ],
        [
          "quayle",
          "portraits/realistic_bg2ee/quayle.png",
          "bg2"
        ],
        [
          "safana",
          "portraits/realistic_bg2ee/safana.png",
          "bg2"
        ],
        [
          "sharteel",
          "portraits/realistic_bg2ee/shartel.png",
          "bg2"
        ],
        [
          "skie",
          "portraits/realistic_bg2ee/skie.png",
          "bg2"
        ],
        [
          "tiax",
          "portraits/realistic_bg2ee/tiax.png",
          "bg2"
        ],
        [
          "xan",
          "portraits/realistic_bg2ee/xan.png",
          "bg2"
        ],
        [
          "xzar",
          "portraits/realistic_bg2ee/xzar.png",
          "bg2"
        ],
        [
          "yeslick",
          "portraits/realistic_bg2ee/yeslick.png",
          "bg2"
        ],
        [
          "illasera",
          "portraits/realistic_bg2ee/illisar.png",
          "tob"
        ],
        [
          "dorn",
          "portraits/realistic_bg2ee/dorn.png",
          "bg2"
        ],
        [
          "neera",
          "portraits/realistic_bg2ee/neera.png",
          "bg2"
        ],
        [
          "rasaad",
          "portraits/realistic_bg2ee/rasaad.png",
          "bg2"
        ],
        [
          "hexxat",
          "portraits/realistic_bg2ee/ohhex.png",
          "bg2"
        ],
        [
          "hexxat",
          "portraits/realistic_bg2ee/ohhexx.png",
          "bg2"
        ],
        [
          "wilson",
          "portraits/realistic_bg2ee/wilson.png",
          "bg2"
        ],
        [
          "balthazar",
          "portraits/realistic_bg2ee/balthaz.png",
          "tob"
        ],
        [
          "gromnir",
          "portraits/realistic_bg2ee/gromnir.png",
          "bg2"
        ],
        [
          "melissan",
          "portraits/realistic_bg2ee/mel_bad.png",
          "tob"
        ],
        [
          "sendai",
          "portraits/realistic_bg2ee/sendai.png",
          "tob"
        ],
        [
          "solar",
          "portraits/realistic_bg2ee/solar.png",
          "tob"
        ],
        [
          "yaga-shura",
          "portraits/realistic_bg2ee/yagashr.png",
          "tob"
        ],
        [
          "abazigal",
          "portraits/realistic_bg2ee/abazhal.png",
          "tob"
        ]
      ]
    },
    "pc": {
      "0": {
        "label": "Realistic Portraits: BG2EE PC Portraits",
        "images": [
          "portraits/realistic_bg2ee/bdorcf1.png",
          "portraits/realistic_bg2ee/bdorcm1.png",
          "portraits/realistic_bg2ee/bdshaf1.png",
          "portraits/realistic_bg2ee/bdtma.png",
          "portraits/realistic_bg2ee/bdtmb.png",
          "portraits/realistic_bg2ee/bdtmc.png",
          "portraits/realistic_bg2ee/bdtmd.png",
          "portraits/realistic_bg2ee/bdtme.png",
          "portraits/realistic_bg2ee/bdtmf.png",
          "portraits/realistic_bg2ee/bdtmg.png",
          "portraits/realistic_bg2ee/bdtmh.png",
          "portraits/realistic_bg2ee/bdtmi.png",
          "portraits/realistic_bg2ee/bdtmj.png",
          "portraits/realistic_bg2ee/bdtmk.png",
          "portraits/realistic_bg2ee/gendwrf.png",
          "portraits/realistic_bg2ee/genmelf.png",
          "portraits/realistic_bg2ee/genmhlf.png",
          "portraits/realistic_bg2ee/man1.png",
          "portraits/realistic_bg2ee/man2.png",
          "portraits/realistic_bg2ee/manley0.png",
          "portraits/realistic_bg2ee/manley1.png",
          "portraits/realistic_bg2ee/manley2.png",
          "portraits/realistic_bg2ee/manley3.png",
          "portraits/realistic_bg2ee/manley4.png",
          "portraits/realistic_bg2ee/manley5.png",
          "portraits/realistic_bg2ee/manley6.png",
          "portraits/realistic_bg2ee/manley7.png",
          "portraits/realistic_bg2ee/manley8.png",
          "portraits/realistic_bg2ee/manley9.png",
          "portraits/realistic_bg2ee/manleyx.png",
          "portraits/realistic_bg2ee/woman1.png",
          "portraits/realistic_bg2ee/woman2.png",
          "portraits/realistic_bg2ee/yanner1.png",
          "portraits/realistic_bg2ee/yanner2.png",
          "portraits/realistic_bg2ee/yanner3.png",
          "portraits/realistic_bg2ee/yanner4.png",
          "portraits/realistic_bg2ee/yanner5.png",
          "portraits/realistic_bg2ee/yanner6.png"
        ]
      }
    }
  },
  "u": "https://www.nexusmods.com/baldursgate2ee/mods/76",
  "a": "NolSol",
  "sum": "AI-generated realistic portrait replacements for BG2:EE NPCs. Override-only mod — place files manually in the game's override folder.",
  "ph": [
    "SoA",
    "ToB"
  ],
  "au": "NolSol",
  "dl": "https://www.nexusmods.com/baldursgate2ee/mods/76",
  "tags": [
    "portraits"
  ],
  "langs": {
    "en": 0
  },
  "co": [
    {
      "n": "Realistic Portraits for BG2EE",
      "cn": 0
    }
  ]
}