{
  "i": 816,
  "t": "Shohy's_Custom_Platform",
  "sv": 1,
  "ord": 710,
  "c": "POST-TACTICAL TWEAKS",
  "n": "Shohy's Custom Platform",
  "langs": {
    "en": 0,
    "zh-cn": 1
  },
  "u": "https://github.com/shohysie/Shohy-s_Custom_Platform",
  "a": "Shohy",
  "sum": "This mod modifies combat and spell casting. Enemies can now use innate abilities.",
  "tags": [
    "tweak"
  ],
  "ph": [
    "BG1",
    "SoD",
    "SoA",
    "ToB"
  ],
  "dl": "https://github.com/shohysie/Shohy-s_Custom_Platform",
  "no": "This mod modifies combat and spell casting. Enemies can now use innate abilities.",
  "au": "shohy",
  "co": [
    {
      "n": "Shohy's customized adjustment platform (base for functional modules)",
      "cn": 0,
      "wf": "Shohy's_Custom_Platform",
      "wp": "Shohy's_Custom_Platform\\SETUP-Shohy's_Custom_Platform.tp2",
      "wc": 0,
      "wq": "lcc-github",
      "g": "Base Platform",
      "no": "Detect game version automatically"
    },
    {
      "n": "Shohy's customized adjustment platform (base for functional modules)",
      "cn": 1,
      "wf": "Shohy's_Custom_Platform",
      "wp": "Shohy's_Custom_Platform\\SETUP-Shohy's_Custom_Platform.tp2",
      "wc": 1,
      "wq": "lcc-github",
      "g": "Base Platform",
      "no": "Manual setup"
    },
    {
      "n": "Detected incompatible old version of Weapon Style Rebalance, please uninstall it first",
      "cn": 2,
      "wf": "Shohy's_Custom_Platform",
      "wp": "Shohy's_Custom_Platform\\SETUP-Shohy's_Custom_Platform.tp2",
      "wc": 2,
      "wq": "lcc-github"
    },
    {
      "n": "Enemy stats grow with protagonist XP",
      "cn": 3,
      "wf": "Shohy's_Custom_Platform",
      "wp": "Shohy's_Custom_Platform\\SETUP-Shohy's_Custom_Platform.tp2",
      "wc": 3,
      "wq": "lcc-github",
      "no": "Enemies scale with player level"
    },
    {
      "n": "Kill XP granted to last attacker",
      "cn": 4,
      "wf": "Shohy's_Custom_Platform",
      "wp": "Shohy's_Custom_Platform\\SETUP-Shohy's_Custom_Platform.tp2",
      "wc": 4,
      "wq": "lcc-github",
      "no": "Only the character landing the killing blow gets XP"
    },
    {
      "n": "Rebalance for Weapon Styles and Detailed Adjustments for Weapon Types",
      "cn": 5,
      "wf": "Shohy's_Custom_Platform",
      "wp": "Shohy's_Custom_Platform\\SETUP-Shohy's_Custom_Platform.tp2",
      "wc": 5,
      "wq": "lcc-github"
    },
    {
      "n": "(Recommended) No more proficiency points but automatically reduce one point on 2 and 3 ranks of each Weapon Style, in exchange for extra benefits",
      "cn": 6,
      "wf": "Shohy's_Custom_Platform",
      "wp": "Shohy's_Custom_Platform\\SETUP-Shohy's_Custom_Platform.tp2",
      "wc": 6,
      "wq": "lcc-github",
      "g": "Proficiency Points"
    },
    {
      "n": "More proficiency points, not compatible with other MODs that adjust Weapon Styles",
      "cn": 7,
      "wf": "Shohy's_Custom_Platform",
      "wp": "Shohy's_Custom_Platform\\SETUP-Shohy's_Custom_Platform.tp2",
      "wc": 7,
      "wq": "lcc-github",
      "g": "Proficiency Points"
    },
    {
      "n": "Available only for EE series",
      "cn": 8,
      "wf": "Shohy's_Custom_Platform",
      "wp": "Shohy's_Custom_Platform\\SETUP-Shohy's_Custom_Platform.tp2",
      "wc": 8,
      "wq": "lcc-github",
      "no": "EE-only tweaks and fixes"
    }
  ],
  "gh": {
    "o": "shohysie",
    "r": "Shohy-s_Custom_Platform"
  }
}
