{
  "i": 817,
  "t": "Skills_and_Proficiencies",
  "sv": 1,
  "ord": 760,
  "c": "PRE-TACTICAL TWEAKS",
  "n": "Skills and Proficiencies",
  "langs": {
    "en": 0
  },
  "u": "https://github.com/Grammarsalad/IE_Skillz/",
  "a": "Grammarsalad",
  "sum": "This is a mod that adds a number of special abilities and thief-like skills to the game (for thieves and non-thieves).",
  "tags": [
    "tweak"
  ],
  "ph": [
    "BG1",
    "SoD",
    "SoA",
    "ToB"
  ],
  "dl": "https://github.com/Grammarsalad/IE_Skillz/",
  "no": "This is a mod that adds a number of special abilities and thief-like skills to the game (for thieves and non-thieves).",
  "au": "SubtleD",
  "co": [
    {
      "n": "Install Component 101: Skill System: Weapon Proficiency Menu",
      "cn": 101,
      "wf": "Skills_and_Proficiencies",
      "wp": "Skills_and_Proficiencies\\SetUp-Skills_and_Proficiencies.tp2",
      "wc": 101,
      "wq": "lcc-github",
      "g": "Skills & Proficiencies: 101-107: Skill System"
    },
    {
      "n": "Install Component 102: Skill System:",
      "cn": 102,
      "wf": "Skills_and_Proficiencies",
      "wp": "Skills_and_Proficiencies\\SetUp-Skills_and_Proficiencies.tp2",
      "wc": 102,
      "wq": "lcc-github",
      "g": "Skills & Proficiencies: 101-107: Skill System"
    },
    {
      "n": "Install Component 201: Basic Weapon Mastery: Standard",
      "cn": 201,
      "wf": "Skills_and_Proficiencies",
      "wp": "Skills_and_Proficiencies\\SetUp-Skills_and_Proficiencies.tp2",
      "wc": 201,
      "wq": "lcc-github",
      "g": "Skills & Proficiencies: 201-207: Weapon Mastery"
    },
    {
      "n": "Install Component 202: Basic Weapon Mastery: Everybody is Kung Fu Fighting",
      "cn": 202,
      "wf": "Skills_and_Proficiencies",
      "wp": "Skills_and_Proficiencies\\SetUp-Skills_and_Proficiencies.tp2",
      "wc": 202,
      "wq": "lcc-github",
      "g": "Skills & Proficiencies: 201-207: Weapon Mastery"
    },
    {
      "n": "Install Component 203: Basic Tier-Based Weapon Mastery: Standard (Non-EEEx)",
      "cn": 203,
      "wf": "Skills_and_Proficiencies",
      "wp": "Skills_and_Proficiencies\\SetUp-Skills_and_Proficiencies.tp2",
      "wc": 203,
      "wq": "lcc-github",
      "g": "Skills & Proficiencies: 201-207: Weapon Mastery"
    },
    {
      "n": "Install Component 204: Basic Tier-Based Weapon Mastery (EEEx Required)",
      "cn": 204,
      "wf": "Skills_and_Proficiencies",
      "wp": "Skills_and_Proficiencies\\SetUp-Skills_and_Proficiencies.tp2",
      "wc": 204,
      "wq": "lcc-github",
      "g": "Skills & Proficiencies: 201-207: Weapon Mastery"
    },
    {
      "n": "Install Component 205: No Cows Tier-Based Weapon Mastery: Standard (Non-EEEx)",
      "cn": 205,
      "wf": "Skills_and_Proficiencies",
      "wp": "Skills_and_Proficiencies\\SetUp-Skills_and_Proficiencies.tp2",
      "wc": 205,
      "wq": "lcc-github",
      "g": "Skills & Proficiencies: 201-207: Weapon Mastery"
    },
    {
      "n": "Install Component 206: No Cows Tier-Based Weapon Mastery (EEEx Required)",
      "cn": 206,
      "wf": "Skills_and_Proficiencies",
      "wp": "Skills_and_Proficiencies\\SetUp-Skills_and_Proficiencies.tp2",
      "wc": 206,
      "wq": "lcc-github",
      "g": "Skills & Proficiencies: 201-207: Weapon Mastery"
    },
    {
      "n": "Install Component 207: Class Based Weapon Mastery",
      "cn": 207,
      "wf": "Skills_and_Proficiencies",
      "wp": "Skills_and_Proficiencies\\SetUp-Skills_and_Proficiencies.tp2",
      "wc": 207,
      "wq": "lcc-github",
      "g": "Skills & Proficiencies: 201-207: Weapon Mastery"
    }
  ],
  "gh": {
    "o": "Grammarsalad",
    "r": "IE_Skillz"
  }
}
