{
  "i": 552,
  "t": "thoghma",
  "sv": 1,
  "ord": 640,
  "c": "QUEST MODS BG2",
  "n": "A Quest in the Service of Oghma",
  "langs": {
    "fr": 0,
    "de": 1,
    "en": 2,
    "es": 3,
    "it": 4,
    "ru": 5
  },
  "cl": [
    {
      "d": "2026-03-10",
      "m": "Added from Infinity Insanity WeiDU logs"
    }
  ],
  "u": "https://www.baldursgateworld.fr/viewtopic.php?t=24078",
  "a": "Thot",
  "v": "v1.7",
  "sum": "Adds a small quest given by a new monk at the Temple of Oghma, offering additional powers as a reward, with NPC commentary throughout the game.",
  "tags": [
    "story"
  ],
  "ph": [
    "SoA"
  ],
  "dl": "https://www.baldursgateworld.fr/viewtopic.php?t=24078",
  "au": "Deratiseur",
  "no": "Adds a small quest given by a new monk at the Temple of Oghma, offering additional powers as a reward, with NPC commentary throughout the game.",
  "co": [
    {
      "n": "A Quest in the service of Oghma",
      "tp2n": "Quete au service d'Oghma",
      "cn": 0,
      "wf": "thoghma",
      "wp": "thoghma\\setup-thoghma.tp2",
      "wc": 0,
      "no": "Not EET compatible. Requires BGII/ToB/BGT/BG2EE only.",
      "games": [
        "bg2ee",
        "bgt",
        "soa",
        "tob"
      ]
    }
  ]
}