{
  "i": 548,
  "t": "Yasraena",
  "sv": 1,
  "ord": 860,
  "c": "NEW NPC MODS",
  "n": "Yasraena NPC",
  "langs": {
    "en": 0,
    "de": 1,
    "fr": 2,
    "es": 3,
    "ru": 4,
    "pl": 5
  },
  "no": "Chaotic Good Female Drow Fighter.Note that taking Yasraena in the starting dungeon of Shadows of Amn (“Chateau Irenicus”) is required to progress through her content, and she never returns to the part...",
  "cl": [
    {
      "d": "2026-03-10",
      "m": "Added from Infinity Insanity WeiDU logs"
    }
  ],
  "pt": {
    "npc": {
      "0": [
        [
          "yasraena",
          "portraits/yasraena/yasraen.png",
          "bg2"
        ]
      ]
    }
  },
  "u": "https://github.com/RoxanneSHS/YasraenaEET",
  "a": "gilalion",
  "v": "v21",
  "sum": "Adds Yasraena, a drow fighter, as a joinable BG2 NPC with romance and content exploring surface-drow culture clash.",
  "tags": [
    "npc"
  ],
  "ph": [
    "SoA",
    "ToB"
  ],
  "au": "gilalion",
  "dl": "https://github.com/RoxanneSHS/YasraenaEET",
  "co": [
    {
      "n": "Yasraena",
      "cn": 0,
      "wf": "YASRAENA",
      "wp": "YASRAENA\\SETUP-YASRAENA.TP2",
      "wc": 0,
      "tp2n": "Yasraena"
    }
  ],
  "gh": {
    "o": "RoxanneSHS",
    "r": "YasraenaEET"
  }
}
